Metadata-Version: 2.1
Name: sagenet
Version: 0.1.1
Summary: Spatial reconstruction of dissociated single-cell data
Home-page: https://github.com/MarioniLab/sagenet
Author: Elyas Heidari
Author-email: eheidari@student.ethz.ch
License: MIT
Download-URL: https://github.com/MarioniLab/sagenet/archive/refs/tags/SageNet_v0.1.0.1.tar.gz
Project-URL: Documentation, https://sagenet.readthedocs.io/en/latest
Project-URL: Source Code, https://github.com/MarioniLab/sagenet
Keywords: bio-informatics,single-cell,single-cell data analysis,spatial data analysis,spatial transcriptomics
Platform: Linux
Platform: MacOSX
Classifier: Development Status :: 5 - Production/Stable
Classifier: Intended Audience :: Science/Research
Classifier: Natural Language :: English
Classifier: License :: OSI Approved :: BSD License
Classifier: Operating System :: POSIX :: Linux
Classifier: Operating System :: MacOS :: MacOS X
Classifier: Typing :: Typed
Classifier: Programming Language :: Python :: 3.6
Classifier: Programming Language :: Python :: 3.7
Classifier: Programming Language :: Python :: 3.8
Classifier: Programming Language :: Python :: 3.9
Classifier: Environment :: Console
Classifier: Framework :: Jupyter
Classifier: Intended Audience :: Science/Research
Classifier: Topic :: Scientific/Engineering :: Bio-Informatics
Classifier: Topic :: Scientific/Engineering :: Visualization
